whey/mixin/paths.py
whey/mixin/__init__.py
whey_mixin-0.1.3.dist-info/entry_points.txt
whey_mixin-0.1.3.dist-info/LICENSE
whey_mixin-0.1.3.dist-info/METADATA
whey_mixin-0.1.3.dist-info/top_level.txt
whey_mixin-0.1.3.dist-info/WHEEL
whey_mixin-0.1.3.dist-info/RECORD
